{
  "name": "VotingEvent/gtGbHWcGNGWw3tNi1Asb/VotingObject/f1voUguRubJ41arF2u1o_img",
  "bucket": "anh-election-app.appspot.com",
  "metageneration": 1,
  "generation": 1642639927686,
  "contentType": "application/octet-stream",
  "storageClass": "STANDARD",
  "contentDisposition": "inline",
  "contentEncoding": "identity",
  "downloadTokens": [
    "cfa45954-c5ce-4a73-9e66-cd35f8e8950e"
  ],
  "etag": "someETag",
  "timeCreated": "2022-01-20T00:52:07.685Z",
  "updated": "2022-01-20T00:52:07.687Z",
  "size": 41157,
  "md5Hash": "uXV+6f4CKqvyvx48/BAeoQ==",
  "crc32c": "4079744207"
}